[{"article":"庆余年","views":845516,"rank":3},{"article":"多功能老婆","views":520146,"rank":5},{"article":"想見你 (電視劇)","views":456169,"rank":6},{"article":"高以翔","views":417947,"rank":7},{"article":"愛的迫降","views":412576,"rank":8},{"article":"謝和弦","views":346082,"rank":9},{"article":"鬼滅之刃","views":341152,"rank":10},{"article":"2020年中華民國總統選舉","views":279687,"rank":12},{"article":"葉問","views":275494,"rank":13},{"article":"中華電信MOD","views":263654,"rank":14},{"article":"葉問4","views":245100,"rank":15},{"article":"遠東航空","views":239799,"rank":16},{"article":"楊蕙如","views":235405,"rank":17},{"article":"吳怡農","views":209385,"rank":18},{"article":"炮仔聲 (台灣電視劇)","views":206485,"rank":19},{"article":"韓國瑜","views":199362,"rank":20},{"article":"多情城市","views":199117,"rank":21},{"article":"冰雪奇緣2","views":189444,"rank":22},{"article":"习近平","views":185897,"rank":23},{"article":"Grand Maison東京","views":184361,"rank":24},{"article":"VIP (韓國電視劇)","views":183966,"rank":25},{"article":"剑王朝 (电视剧)","views":179679,"rank":26},{"article":"德魯納酒店","views":179424,"rank":27},{"article":"格蕾塔·通贝里","views":179168,"rank":28},{"article":"鹤唳华亭","views":178955,"rank":29},{"article":"刀劍神域","views":175926,"rank":30},{"article":"這個勇者明明超TUEEE卻過度謹慎","views":168229,"rank":31},{"article":"2019年世界羽聯世界巡迴賽總決賽","views":167281,"rank":32},{"article":"曾博恩","views":166643,"rank":33},{"article":"从前有座灵剑山 (网络剧)","views":166278,"rank":34},{"article":"大明風華","views":164438,"rank":35},{"article":"蔡英文","views":162812,"rank":36},{"article":"俗女養成記","views":160185,"rank":37},{"article":"吳斯懷","views":157779,"rank":38},{"article":"凤弈","views":157678,"rank":39},{"article":"獵魔士 (電視劇)","views":156326,"rank":40},{"article":"美味滿閣","views":155190,"rank":41},{"article":"中国中央电视台","views":154508,"rank":42},{"article":"STAR WARS：天行者的崛起","views":151678,"rank":43},{"article":"陈情令","views":151612,"rank":44},{"article":"Wiki","views":150601,"rank":45},{"article":"星際大戰","views":147668,"rank":46},{"article":"黎小田","views":147157,"rank":47},{"article":"宋楚瑜","views":145599,"rank":48},{"article":"六四事件","views":144859,"rank":49},{"article":"北京广播电视台","views":144356,"rank":50},{"article":"中華民國","views":142329,"rank":51},{"article":"2020年中華民國總統選舉民意調查","views":141635,"rank":53},{"article":"延禧攻略","views":141370,"rank":54},{"article":"反對逃犯條例修訂草案運動","views":140767,"rank":55},{"article":"野蠻遊戲：全面晉級","views":139167,"rank":56},{"article":"鄧紫棋","views":138628,"rank":57},{"article":"草榴社区","views":136326,"rank":58},{"article":"周柏豪","views":135921,"rank":59},{"article":"HIStory3","views":135882,"rank":60},{"article":"肖戰","views":135426,"rank":61},{"article":"鬼滅之刃角色列表","views":133121,"rank":62},{"article":"炫彬","views":131359,"rank":63},{"article":"IU (艺人)","views":129646,"rank":64},{"article":"中华人民共和国","views":129525,"rank":65},{"article":"網紅的瘋狂世界","views":128256,"rank":66},{"article":"2019年Running Man節目列表","views":127604,"rank":67},{"article":"冬至","views":126618,"rank":68},{"article":"防彈少年團","views":124569,"rank":69},{"article":"2016年中華民國總統選舉","views":124456,"rank":70},{"article":"許光漢","views":124269,"rank":71},{"article":"圣诞节","views":123274,"rank":72},{"article":"意外發現的一天","views":121432,"rank":73},{"article":"李小龙","views":120867,"rank":74},{"article":"孙小果","views":119102,"rank":75},{"article":"知否？知否？应是绿肥红瘦","views":115761,"rank":76},{"article":"陳柏惟","views":114990,"rank":77},{"article":"2020年中華民國立法委員選舉","views":114400,"rank":78},{"article":"VAGABOND (電視劇)","views":113607,"rank":79},{"article":"巧克力 (韓國電視劇)","views":112630,"rank":80},{"article":"高爾宣","views":112243,"rank":81},{"article":"天堂的微笑","views":111958,"rank":82},{"article":"愛·回家之開心速遞","views":110170,"rank":83},{"article":"返校 (電影)","views":110126,"rank":84},{"article":"有瑕疵的人們","views":108665,"rank":85},{"article":"中華民國媒體列表","views":108546,"rank":86},{"article":"梦回","views":107155,"rank":87},{"article":"香港","views":106059,"rank":88},{"article":"孫藝真","views":105179,"rank":89},{"article":"台灣基進","views":104999,"rank":90},{"article":"野蠻遊戲：瘋狂叢林","views":102311,"rank":91},{"article":"星宇航空","views":101633,"rank":92},{"article":"極道千金","views":99413,"rank":93},{"article":"Running Man","views":98978,"rank":94},{"article":"山东号航空母舰","views":98057,"rank":95},{"article":"小丑 (電影)","views":96299,"rank":96},{"article":"独孤皇后 (电视剧)","views":95432,"rank":97},{"article":"张若昀","views":95335,"rank":98},{"article":"博恩夜夜秀","views":94733,"rank":99},{"article":"鬼影特攻：以暴制暴","views":90591,"rank":101},{"article":"四川航空8633号班机事故","views":90550,"rank":102},{"article":"蔣萬安","views":90264,"rank":103},{"article":"臺灣","views":90141,"rank":104},{"article":"如懿傳","views":89721,"rank":105},{"article":"女兵日記女力報到","views":87601,"rank":106},{"article":"楊千嬅","views":86449,"rank":107},{"article":"刀劍神域角色列表","views":86115,"rank":108},{"article":"請輸入檢索詞WWW","views":85480,"rank":109},{"article":"山茶花開時","views":85185,"rank":110},{"article":"賴品妤","views":84526,"rank":111},{"article":"乾隆帝","views":83948,"rank":112},{"article":"我的英雄學院","views":83869,"rank":113},{"article":"Doctor-X～外科醫·大門未知子～","views":83527,"rank":114},{"article":"在不瘋狂就等死","views":83059,"rank":115},{"article":"賽道狂人","views":82973,"rank":116},{"article":"鏡子森林","views":82650,"rank":117},{"article":"愛爾蘭人 (2019年電影)","views":82639,"rank":118},{"article":"Mamamoo","views":82220,"rank":119},{"article":"冰雪奇缘","views":81865,"rank":120},{"article":"香港電台","views":81311,"rank":121},{"article":"2018－2019年中美贸易战","views":80913,"rank":122},{"article":"澳門","views":80796,"rank":123},{"article":"TWICE","views":80182,"rank":124},{"article":"延禧攻略角色列表","views":79658,"rank":125},{"article":"薄熙来","views":78956,"rank":126},{"article":"BEASTARS","views":78740,"rank":127},{"article":"車璌河","views":77063,"rank":128},{"article":"丫鬟大聯盟","views":76980,"rank":129},{"article":"甄子丹","views":76616,"rank":130},{"article":"EXO","views":76439,"rank":131},{"article":"名偵探柯南動畫集數列表","views":76399,"rank":132},{"article":"明星大偵探","views":76339,"rank":133},{"article":"戴祖儀","views":76274,"rank":134},{"article":"葉準","views":76080,"rank":135},{"article":"過街英雄","views":75712,"rank":136},{"article":"綜藝玩很大","views":75033,"rank":137},{"article":"堅離地愛堅離地","views":75015,"rank":138},{"article":"關於我轉生變成史萊姆這檔事","views":74146,"rank":139},{"article":"澳門輕軌","views":73492,"rank":140},{"article":"少年的你","views":73375,"rank":141},{"article":"李沁","views":73346,"rank":142},{"article":"中国大陆电视剧列表 (2019年)","views":73277,"rank":143},{"article":"新疆再教育营","views":72797,"rank":144},{"article":"明宣宗","views":72528,"rank":145},{"article":"李子柒","views":72304,"rank":146},{"article":"皓镧传","views":72271,"rank":147},{"article":"日本","views":72142,"rank":148},{"article":"明成祖","views":71949,"rank":149},{"article":"毛泽东","views":71886,"rank":150},{"article":"五月天","views":71559,"rank":151},{"article":"Super Junior","views":70599,"rank":152},{"article":"公共電視文化事業基金會","views":70154,"rank":153},{"article":"Dr.STONE 新石紀","views":70140,"rank":154},{"article":"Running Man節目列表","views":69438,"rank":155},{"article":"2019年12月26日日食","views":69200,"rank":156},{"article":"王淺秋","views":68998,"rank":157},{"article":"張善政","views":68972,"rank":158},{"article":"七大罪 (漫畫)","views":68780,"rank":159},{"article":"婚姻故事","views":68149,"rank":160},{"article":"文化大革命","views":67590,"rank":161},{"article":"周杰倫","views":67446,"rank":162},{"article":"一起出发吧","views":67322,"rank":163},{"article":"鋒迴路轉","views":67176,"rank":164},{"article":"解決師","views":67118,"rank":165},{"article":"去年聖誕節 (電影)","views":66759,"rank":166},{"article":"曼達洛人 (電視劇)","views":66617,"rank":167},{"article":"维基百科","views":66326,"rank":168},{"article":"ONE PIECE","views":65910,"rank":169},{"article":"王梓軒","views":65843,"rank":170},{"article":"日本動畫列表 (2020年)","views":65767,"rank":171},{"article":"認識的哥哥","views":65024,"rank":172},{"article":"王一博","views":64973,"rank":173},{"article":"柯佳嬿","views":64785,"rank":174},{"article":"习明泽","views":64635,"rank":175},{"article":"葉正","views":64545,"rank":176},{"article":"蔡依林","views":64307,"rank":177},{"article":"陳綺貞","views":63516,"rank":178},{"article":"歡樂無法黨","views":63240,"rank":179},{"article":"如懿傳角色列表","views":63011,"rank":180},{"article":"中国机长","views":63006,"rank":181},{"article":"香港航空","views":62872,"rank":182},{"article":"新加坡","views":62750,"rank":183},{"article":"杨幂","views":62671,"rank":184},{"article":"五十音","views":62478,"rank":185},{"article":"寄生上流","views":62477,"rank":186},{"article":"从前有座灵剑山","views":62413,"rank":187},{"article":"李一桐","views":62091,"rank":188},{"article":"我们的歌 (综艺节目)","views":61364,"rank":189},{"article":"環狀線 (台北捷運)","views":61250,"rank":190},{"article":"焦佳弘","views":61007,"rank":191},{"article":"百度","views":60723,"rank":192},{"article":"抓住幽靈","views":60613,"rank":193},{"article":"應采兒","views":60124,"rank":194},{"article":"木村拓哉","views":59366,"rank":195},{"article":"我們與惡的距離","views":59188,"rank":196},{"article":"進擊的巨人","views":59059,"rank":197},{"article":"精神病患者日記","views":59048,"rank":198},{"article":"(G)I-DLE","views":58898,"rank":199},{"article":"郭文贵","views":58656,"rank":200},{"article":"大麻","views":57843,"rank":201},{"article":"JoJo的奇妙冒险","views":57769,"rank":202},{"article":"越南","views":57554,"rank":203},{"article":"蔣中正","views":57509,"rank":204},{"article":"白石麻衣","views":57404,"rank":205},{"article":"逃出魔幻紀","views":57324,"rank":206},{"article":"明朝","views":57100,"rank":207},{"article":"江泽民","views":57051,"rank":208},{"article":"葉問3","views":56977,"rank":209},{"article":"罪夢者","views":56958,"rank":210},{"article":"香港人權與民主法案","views":56926,"rank":211},{"article":"坂井泉水","views":56909,"rank":212},{"article":"2012年中華民國總統選舉","views":56647,"rank":213},{"article":"AOA","views":56579,"rank":214},{"article":"陳宜民","views":56530,"rank":215},{"article":"清朝","views":56494,"rank":216},{"article":"唐納·川普","views":56455,"rank":217},{"article":"SARS事件","views":56401,"rank":218},{"article":"劉奕兒","views":56157,"rank":219},{"article":"Stove League","views":55950,"rank":220},{"article":"孤單又燦爛的神－鬼怪","views":55872,"rank":221},{"article":"台灣民眾黨 (2019年)","views":55843,"rank":222},{"article":"朝鮮浪漫喜劇–綠豆傳","views":55804,"rank":223},{"article":"趙麗穎","views":55625,"rank":224},{"article":"黃國昌","views":55493,"rank":225},{"article":"五等分的新娘","views":55285,"rank":226},{"article":"马来西亚","views":55184,"rank":227},{"article":"E-Hentai","views":55059,"rank":228},{"article":"鍾明軒","views":54924,"rank":229},{"article":"于淼","views":54815,"rank":230},{"article":"蔣經國","views":54198,"rank":231},{"article":"火影忍者疾風傳動畫集數列表","views":54156,"rank":232},{"article":"Red Velvet","views":53581,"rank":233},{"article":"律政新人王II","views":53549,"rank":234},{"article":"美国","views":53532,"rank":235},{"article":"揀擇－女人們的戰爭","views":53529,"rank":236},{"article":"迪丽热巴","views":53511,"rank":237},{"article":"5G","views":53475,"rank":238},{"article":"孫中山","views":53470,"rank":239},{"article":"中國國民黨","views":53113,"rank":240},{"article":"第九分局","views":52635,"rank":241},{"article":"蘇慧倫","views":52616,"rank":242},{"article":"YouTube","views":52562,"rank":243},{"article":"美麗島事件","views":52164,"rank":244},{"article":"喜歡本大爺的竟然就妳一個？","views":52035,"rank":245},{"article":"TvN Asia","views":51970,"rank":246},{"article":"邓伦","views":51660,"rank":247},{"article":"邱威傑","views":51541,"rank":248},{"article":"新潮流系","views":51320,"rank":249},{"article":"華為251事件","views":51164,"rank":250},{"article":"亲爱的，热爱的","views":51124,"rank":251},{"article":"2019年香港區議會選舉","views":50987,"rank":252},{"article":"陳水扁","views":50644,"rank":253},{"article":"CATS貓","views":50574,"rank":254},{"article":"自由亚洲电台","views":50559,"rank":255},{"article":"死亡擱淺","views":50515,"rank":256},{"article":"葉問 (電影)","views":50472,"rank":257},{"article":"PSYCHO-PASS","views":50397,"rank":258},{"article":"民主進步黨","views":50317,"rank":259},{"article":"陳零九","views":50229,"rank":260},{"article":"切尔诺贝利核事故","views":49737,"rank":261},{"article":"李登輝","views":49672,"rank":262},{"article":"ONE PIECE動畫集數列表","views":49616,"rank":263},{"article":"食戟之靈","views":49542,"rank":264},{"article":"天生一对 (泰国电视剧)","views":49490,"rank":265},{"article":"伊丽莎白二世","views":49484,"rank":266},{"article":"易烊千玺","views":49372,"rank":267},{"article":"99億的女人","views":49249,"rank":268},{"article":"伊莉討論區","views":49134,"rank":269},{"article":"初恋那件小事 (电视剧)","views":49134,"rank":269},{"article":"俄罗斯","views":48887,"rank":271},{"article":"哈利·波特","views":48843,"rank":272},{"article":"中国共产党","views":48788,"rank":273},{"article":"蒙面唱將猜猜猜 (第四季)","views":48660,"rank":274},{"article":"女力報到－小資女上班記","views":48649,"rank":275},{"article":"ASCII","views":48477,"rank":276},{"article":"乌鲁木齐七五事件","views":48462,"rank":277},{"article":"楊丞琳","views":48087,"rank":278},{"article":"日本動畫列表 (2019年)","views":48002,"rank":279},{"article":"陳玉珍 (金門)","views":47980,"rank":280},{"article":"法轮功","views":47890,"rank":281},{"article":"鄭家純 (藝人)","views":47890,"rank":281},{"article":"追我吧","views":47795,"rank":283},{"article":"荷兰","views":47677,"rank":284},{"article":"香蜜沉沉燼如霜","views":47669,"rank":285},{"article":"雍正帝","views":47483,"rank":286},{"article":"絕命毒師","views":47479,"rank":287},{"article":"林兆波","views":47261,"rank":288},{"article":"想停止的瞬間：About Time","views":46997,"rank":289},{"article":"STAR WARS：最後的絕地武士","views":46870,"rank":290},{"article":"秦始皇","views":46869,"rank":291},{"article":"許凱","views":46865,"rank":292},{"article":"邱鋒澤","views":46840,"rank":293},{"article":"鄧惠文","views":46839,"rank":294},{"article":"林鄭月娥","views":46802,"rank":295},{"article":"李现","views":46782,"rank":296},{"article":"火影忍者","views":46624,"rank":297},{"article":"律政新人王","views":46622,"rank":298},{"article":"英国","views":46569,"rank":299},{"article":"康熙帝","views":46515,"rank":300},{"article":"我的英雄学院角色列表","views":46460,"rank":301},{"article":"一拳超人","views":46373,"rank":302},{"article":"高嘉瑜","views":46344,"rank":303},{"article":"王嘉爾","views":46327,"rank":304},{"article":"鄭宏輝","views":46320,"rank":305},{"article":"名偵探柯南","views":46163,"rank":306},{"article":"入間同學入魔了！","views":45983,"rank":307},{"article":"假面騎士ZERO-ONE","views":45976,"rank":308},{"article":"三生三世十里桃花 (电视剧)","views":45958,"rank":309},{"article":"許淑華 (臺北市)","views":45869,"rank":310},{"article":"吳卓源","views":45783,"rank":311},{"article":"金錫佑","views":45696,"rank":312},{"article":"蕭若元","views":45683,"rank":313},{"article":"臺灣醫院列表","views":45616,"rank":314},{"article":"孝儀純皇后","views":45543,"rank":315},{"article":"炎炎消防隊","views":45533,"rank":316},{"article":"Kuaizero 老高","views":45493,"rank":317},{"article":"SF9","views":45415,"rank":318},{"article":"三生三世枕上书","views":45329,"rank":319},{"article":"朱晨麗","views":45290,"rank":320},{"article":"邓小平","views":45256,"rank":321},{"article":"朝鲜战争","views":45194,"rank":323},{"article":"全民造星II","views":45187,"rank":324},{"article":"綠黨 (臺灣)","views":45161,"rank":325},{"article":"施柏宇","views":45119,"rank":326},{"article":"安眠書店 (電視劇)","views":45104,"rank":327},{"article":"聖誕夜","views":45058,"rank":328},{"article":"澳大利亚","views":45039,"rank":329},{"article":"王岐山","views":44901,"rank":330},{"article":"三上悠亞","views":44805,"rank":331},{"article":"巨石強森","views":44754,"rank":332},{"article":"TXT (組合)","views":44713,"rank":333},{"article":"Seventeen (組合)","views":44685,"rank":334},{"article":"張榕容","views":44637,"rank":335},{"article":"宋緯恩","views":44529,"rank":336},{"article":"最高法院檢察署特別偵查組","views":44389,"rank":337},{"article":"孝恭章皇后","views":44362,"rank":338},{"article":"2008年中華民國總統選舉","views":44152,"rank":340},{"article":"林俊杰","views":44077,"rank":341},{"article":"孔劉","views":44059,"rank":342},{"article":"明星大偵探第五季節目列表","views":44056,"rank":343},{"article":"第二次世界大战","views":43982,"rank":344},{"article":"蔡宜芳","views":43624,"rank":345},{"article":"馬英九","views":43423,"rank":346},{"article":"林昶佐","views":43395,"rank":347},{"article":"AV女優","views":43388,"rank":348},{"article":"反滲透法草案","views":43231,"rank":349},{"article":"Leverage：詐騙操作團","views":43168,"rank":350},{"article":"Netflix","views":43122,"rank":351},{"article":"蘇啟誠","views":42918,"rank":352},{"article":"大韩民国","views":42911,"rank":353},{"article":"周星馳","views":42855,"rank":354},{"article":"ITZY","views":42695,"rank":355},{"article":"明仁宗","views":42690,"rank":356},{"article":"你那邊怎樣·我這邊OK","views":42530,"rank":357},{"article":"小書痴的下剋上","views":42529,"rank":358},{"article":"蕭亞軒","views":42511,"rank":359},{"article":"翡翠台電視劇集列表 (2010年代)","views":42464,"rank":360},{"article":"第70回NHK紅白歌合戰","views":42376,"rank":361},{"article":"橋本有菜","views":42365,"rank":362},{"article":"Re:從零開始的異世界生活","views":42361,"rank":363},{"article":"謝盈萱","views":42342,"rank":364},{"article":"迈克尔·杰克逊","views":42244,"rank":365},{"article":"入住請敲門","views":42158,"rank":366},{"article":"阿道夫·希特勒","views":42128,"rank":367},{"article":"邱毅","views":42036,"rank":368},{"article":"葉問外傳：張天志","views":42005,"rank":369},{"article":"萊恩·雷諾斯","views":41763,"rank":370},{"article":"史嘉蕾·喬韓森","views":41740,"rank":371},{"article":"臺灣罷免制度","views":41727,"rank":372},{"article":"柯文哲","views":41612,"rank":373},{"article":"OVERLORD (小說)","views":41581,"rank":374},{"article":"印度","views":41548,"rank":375},{"article":"胡锦涛","views":41456,"rank":376},{"article":"遇见王沥川","views":41440,"rank":377},{"article":"SCP基金会","views":41437,"rank":378},{"article":"HUNTER×HUNTER","views":41429,"rank":379},{"article":"南京大屠殺","views":41261,"rank":380},{"article":"2016年中華民國立法委員選舉","views":41201,"rank":381},{"article":"標準差","views":41181,"rank":382},{"article":"台灣YouTube頻道訂閱人數排行榜","views":41169,"rank":383},{"article":"劉德華","views":41105,"rank":384},{"article":"超人高中生們即便在異世界也能從容生存！","views":41065,"rank":385},{"article":"關於我轉生變成史萊姆這檔事角色列表","views":41043,"rank":386},{"article":"內湖隨機殺人事件","views":40844,"rank":387},{"article":"陳國坤","views":40844,"rank":387},{"article":"蕭敬騰","views":40804,"rank":389},{"article":"鳄鱼与牙签鸟","views":40796,"rank":390},{"article":"我們真的學不來！","views":40713,"rank":391},{"article":"李纯 (演员)","views":40441,"rank":392},{"article":"深田詠美","views":40409,"rank":393},{"article":"Fate/Grand Order","views":40317,"rank":394},{"article":"猎魔人","views":40204,"rank":395},{"article":"朱元璋","views":40199,"rank":396},{"article":"中華民國基本工資","views":40193,"rank":397},{"article":"海棠经雨胭脂透","views":40172,"rank":398},{"article":"為美好的世界獻上祝福！","views":40157,"rank":399},{"article":"上原亞衣","views":40148,"rank":400},{"article":"新疆维吾尔自治区","views":40093,"rank":401},{"article":"九二共識","views":40092,"rank":402},{"article":"賴冠霖","views":40061,"rank":403},{"article":"朱迪·加兰","views":39870,"rank":404},{"article":"陈小春","views":39833,"rank":405},{"article":"余湘","views":39626,"rank":406},{"article":"周子瑜","views":39612,"rank":407},{"article":"Black Dog (電視劇)","views":39491,"rank":408},{"article":"維吾爾人權政策法案","views":39472,"rank":409},{"article":"徐子珊","views":39456,"rank":410},{"article":"後宮甄嬛傳 (電視劇)","views":39452,"rank":411},{"article":"杨紫","views":39364,"rank":413},{"article":"河智苑","views":39297,"rank":414},{"article":"躁鬱症","views":39229,"rank":415},{"article":"火星生活 (韓國電視劇)","views":39164,"rank":416},{"article":"王立強事件","views":39096,"rank":417},{"article":"泰国","views":38957,"rank":418},{"article":"陳喬恩","views":38895,"rank":419},{"article":"林予晞","views":38878,"rank":420},{"article":"張國煒","views":38873,"rank":421},{"article":"越南战争","views":38870,"rank":422},{"article":"忠孝節義","views":38844,"rank":423},{"article":"中華民國歷任總統得票率","views":38762,"rank":424},{"article":"不能結婚的男人 (日本電視劇)","views":38730,"rank":425},{"article":"德国","views":38727,"rank":426},{"article":"比莉·艾利什","views":38695,"rank":427},{"article":"加拿大","views":38618,"rank":428},{"article":"我的大叔","views":38599,"rank":429},{"article":"徐智慧 (1984年)","views":38393,"rank":430},{"article":"克娄巴特拉七世","views":38300,"rank":431},{"article":"二二八事件","views":38237,"rank":432},{"article":"凯伦·吉兰","views":38126,"rank":433},{"article":"MIRROR","views":37944,"rank":434},{"article":"張國榮","views":37942,"rank":435},{"article":"中華民國總統","views":37931,"rank":436},{"article":"白卜庭","views":37923,"rank":437},{"article":"IZ*ONE","views":37912,"rank":438},{"article":"李屍朝鮮","views":37820,"rank":439},{"article":"妥瑞症","views":37710,"rank":440},{"article":"家師父一體","views":37648,"rank":441},{"article":"周興哲","views":37638,"rank":442},{"article":"達斯·維達","views":37568,"rank":443},{"article":"七大罪角色列表","views":37517,"rank":444},{"article":"張永成","views":37495,"rank":445},{"article":"华晨宇","views":37489,"rank":446},{"article":"一带一路","views":37457,"rank":447},{"article":"司马懿","views":37436,"rank":448},{"article":"第一次世界大战","views":37388,"rank":449},{"article":"阿滴英文","views":37376,"rank":450},{"article":"中國","views":37347,"rank":451},{"article":"亞當·崔佛","views":37227,"rank":452},{"article":"性交","views":37191,"rank":453},{"article":"洪慈庸","views":37184,"rank":454},{"article":"Facebook","views":37168,"rank":455},{"article":"時代力量","views":37119,"rank":456},{"article":"林志玲","views":37114,"rank":457},{"article":"苏联","views":37080,"rank":458},{"article":"陽光普照","views":37080,"rank":458},{"article":"勒布朗·詹姆斯","views":37003,"rank":460},{"article":"黃錦燊","views":36987,"rank":461},{"article":"人工智能","views":36965,"rank":462},{"article":"圣诞老人","views":36963,"rank":463},{"article":"以色列","views":36913,"rank":464},{"article":"長榮航空","views":36885,"rank":465},{"article":"毛加恩","views":36875,"rank":466},{"article":"ONE PIECE海賊列表","views":36837,"rank":467},{"article":"池昌旭","views":36831,"rank":468},{"article":"愛·回家之開心速遞角色列表","views":36822,"rank":469},{"article":"請融化我吧","views":36667,"rank":470},{"article":"艾滋病","views":36657,"rank":471},{"article":"花江夏樹","views":36646,"rank":472},{"article":"元素周期表","views":36586,"rank":473},{"article":"长安十二时辰","views":36564,"rank":474},{"article":"新垣結衣","views":36498,"rank":475},{"article":"Google","views":36471,"rank":476},{"article":"張鈞甯","views":36411,"rank":477},{"article":"大军师司马懿","views":36334,"rank":478},{"article":"2019年世界羽聯世界巡迴賽","views":36331,"rank":479},{"article":"張華峰","views":36205,"rank":480},{"article":"STAR WARS：原力覺醒","views":36099,"rank":481},{"article":"郭台銘","views":36082,"rank":482},{"article":"周冬雨","views":35986,"rank":484},{"article":"很便宜，千里馬超市","views":35933,"rank":485},{"article":"秀智","views":35898,"rank":486},{"article":"蜡笔小新","views":35881,"rank":487},{"article":"周永康","views":35812,"rank":488},{"article":"沈韋汝","views":35806,"rank":489},{"article":"2004年中華民國總統選舉","views":35786,"rank":490},{"article":"太陽的後裔","views":35776,"rank":491},{"article":"周华健","views":35716,"rank":492},{"article":"GOT7","views":35647,"rank":493},{"article":"軍官·情人","views":35606,"rank":494},{"article":"李佳芬","views":35565,"rank":495},{"article":"雙子殺手","views":35504,"rank":496},{"article":"林書豪","views":35487,"rank":497},{"article":"吳樾 (演員)","views":35468,"rank":498},{"article":"巫师3：狂猎","views":35433,"rank":499},{"article":"守著陽光守著你 (2019年電視劇)","views":35416,"rank":500},{"article":"刺客守則","views":35354,"rank":501},{"article":"陳子見","views":35246,"rank":503},{"article":"蔡易餘","views":35234,"rank":504},{"article":"在地下城尋求邂逅是否搞錯了什麼","views":35126,"rank":505},{"article":"拳願阿修羅","views":35070,"rank":506},{"article":"BLACKPINK","views":35067,"rank":507},{"article":"檢察官內傳","views":35005,"rank":508},{"article":"各国人均国内生产总值列表 (国际汇率)","views":35004,"rank":509},{"article":"2000年中華民國總統選舉","views":34990,"rank":510},{"article":"对习近平的争议","views":34914,"rank":511},{"article":"上海广播电视台","views":34907,"rank":512},{"article":"李棟旭","views":34859,"rank":513},{"article":"灌篮高手","views":34834,"rank":514},{"article":"強弱危機分析","views":34764,"rank":515},{"article":"刘亦菲","views":34682,"rank":516},{"article":"八國聯軍","views":34646,"rank":517},{"article":"機動戰士GUNDAM 鐵血的孤兒","views":34605,"rank":518},{"article":"HUNTER×HUNTER角色列表","views":34603,"rank":519},{"article":"宫崎骏","views":34482,"rank":520},{"article":"唐朝","views":34392,"rank":521},{"article":"張娜拉","views":34335,"rank":522},{"article":"2018年中華民國直轄市長及縣市長選舉","views":34323,"rank":523},{"article":"2020年夏季奥林匹克运动会","views":34273,"rank":524},{"article":"吳思賢 (藝人)","views":34260,"rank":525},{"article":"瑞士","views":34175,"rank":526},{"article":"隋文帝","views":34154,"rank":527},{"article":"謝坤達","views":34138,"rank":528},{"article":"Pornhub","views":34132,"rank":529},{"article":"北大西洋公约组织","views":34076,"rank":530},{"article":"鄧麗君","views":34020,"rank":531},{"article":"Code Geass反叛的魯路修","views":33949,"rank":532},{"article":"葉問2","views":33853,"rank":533},{"article":"青春豬頭少年","views":33816,"rank":534},{"article":"NCT","views":33810,"rank":535},{"article":"区块链","views":33799,"rank":536},{"article":"宇宙少女","views":33740,"rank":537},{"article":"魏大勋","views":33728,"rank":538},{"article":"從前，有個好萊塢","views":33726,"rank":539},{"article":"我家的熊孩子","views":33725,"rank":540},{"article":"正态分布","views":33644,"rank":541},{"article":"阿爾罕布拉宮的回憶 (電視劇)","views":33621,"rank":542},{"article":"朴敏英","views":33585,"rank":543},{"article":"曹操","views":33579,"rank":544},{"article":"朝鲜民主主义人民共和国","views":33545,"rank":545},{"article":"金宵大廈","views":33494,"rank":546},{"article":"SpeXial","views":33486,"rank":547},{"article":"黑色星期五 (购物)","views":33463,"rank":548},{"article":"陈峰","views":33456,"rank":549},{"article":"尹啟相","views":33416,"rank":550},{"article":"ØZI","views":33411,"rank":551},{"article":"漫威电影宇宙","views":33357,"rank":552},{"article":"菅田將暉","views":33341,"rank":553},{"article":"成龍","views":33336,"rank":554},{"article":"土耳其","views":33293,"rank":555},{"article":"賀一誠","views":33265,"rank":556},{"article":"我的愛情治癒記","views":33260,"rank":557},{"article":"艾莎门","views":33209,"rank":558},{"article":"星巴克","views":33205,"rank":559},{"article":"台北101","views":33194,"rank":560},{"article":"柬埔寨","views":33155,"rank":561},{"article":"東南亞職業籃球聯賽","views":33135,"rank":562},{"article":"復仇者聯盟：終局之戰","views":33090,"rank":563},{"article":"勾引社群","views":33084,"rank":564},{"article":"弹劾","views":32955,"rank":565},{"article":"孔曉振","views":32921,"rank":566},{"article":"東京喰種","views":32778,"rank":567},{"article":"梅艷芳","views":32761,"rank":568},{"article":"水行俠 (電影)","views":32750,"rank":569},{"article":"臺北市","views":32748,"rank":570},{"article":"肺炎","views":32598,"rank":571},{"article":"古天樂","views":32592,"rank":572},{"article":"嗨唱转起来","views":32590,"rank":573},{"article":"缅甸","views":32538,"rank":574},{"article":"抖音","views":32504,"rank":575},{"article":"辛芷蕾","views":32400,"rank":576},{"article":"怪奇物語","views":32372,"rank":577},{"article":"LiSA","views":32259,"rank":578},{"article":"MOMOLAND","views":32225,"rank":579},{"article":"李克强","views":32211,"rank":580},{"article":"肛交","views":32179,"rank":581},{"article":"马云","views":32110,"rank":582},{"article":"劉以豪","views":32052,"rank":583},{"article":"具荷拉","views":32036,"rank":584},{"article":"芬兰","views":32015,"rank":585},{"article":"明天會更好","views":31959,"rank":586},{"article":"相澤南","views":31892,"rank":587},{"article":"宋轶","views":31887,"rank":588},{"article":"星際救援","views":31847,"rank":589},{"article":"Astro (韓國音樂團體)","views":31824,"rank":590},{"article":"李婉鈺","views":31806,"rank":591},{"article":"瑯琊榜 (電視劇)","views":31732,"rank":592},{"article":"少女时代","views":31700,"rank":593},{"article":"王陽明 (演員)","views":31674,"rank":594},{"article":"列奥纳多·达·芬奇","views":31653,"rank":595},{"article":"方皓玟","views":31645,"rank":596},{"article":"蒙古国","views":31625,"rank":597},{"article":"李昇基","views":31584,"rank":598},{"article":"Idol Room","views":31527,"rank":599},{"article":"宋慧喬","views":31494,"rank":600},{"article":"唐艺昕","views":31488,"rank":601},{"article":"李相侖","views":31483,"rank":602},{"article":"機動戰士GUNDAM 00","views":31478,"rank":603},{"article":"金秘書為何那樣","views":31462,"rank":604},{"article":"紅毛城","views":31429,"rank":605},{"article":"苗可秀","views":31421,"rank":606},{"article":"Legal High (韓國電視劇)","views":31407,"rank":607},{"article":"黃金有罪","views":31404,"rank":608},{"article":"殺戮都市","views":31394,"rank":609},{"article":"吴青峰","views":31364,"rank":610},{"article":"我不是說了能力要平均值嗎？","views":31249,"rank":611},{"article":"畢書盡","views":31212,"rank":612},{"article":"闪灵 (电影)","views":31181,"rank":613},{"article":"安眠醫生 (電影)","views":31128,"rank":614},{"article":"賴清德","views":31033,"rank":615},{"article":"Sky Castle","views":31018,"rank":616},{"article":"萬福 (電視劇)","views":30972,"rank":617},{"article":"家庭教師HITMAN REBORN! (動畫)","views":30967,"rank":618},{"article":"黛西·蕾德莉","views":30932,"rank":619},{"article":"陳之漢","views":30877,"rank":620},{"article":"海盜灣","views":30857,"rank":621},{"article":"Python","views":30852,"rank":622},{"article":"亞斯伯格症候群","views":30827,"rank":623},{"article":"美人心計","views":30817,"rank":624},{"article":"松下紗榮子","views":30757,"rank":625},{"article":"新西兰","views":30749,"rank":626},{"article":"溥仪","views":30690,"rank":627},{"article":"Angelababy","views":30669,"rank":628},{"article":"中華航空","views":30564,"rank":629},{"article":"陳煒","views":30535,"rank":630},{"article":"李聖經","views":30478,"rank":631},{"article":"蔣孝嚴","views":30475,"rank":632},{"article":"台灣積體電路製造","views":30474,"rank":633},{"article":"AV帝王","views":30418,"rank":634},{"article":"台9線南迴公路拓寬改善後續計畫","views":30386,"rank":635},{"article":"印度尼西亚","views":30376,"rank":636},{"article":"太陽花學運","views":30353,"rank":637},{"article":"高雄市","views":30342,"rank":638},{"article":"李鍾碩","views":30335,"rank":639},{"article":"赵紫阳","views":30266,"rank":640},{"article":"GFRIEND","views":30263,"rank":641},{"article":"魏如萱","views":30263,"rank":641},{"article":"斯德哥爾摩症候群","views":30259,"rank":643},{"article":"王浩宇","views":30251,"rank":644},{"article":"椎名空","views":30244,"rank":645},{"article":"陳子玄","views":30188,"rank":646},{"article":"立法院","views":30153,"rank":647},{"article":"埃及艳后 (电影)","views":30102,"rank":648},{"article":"孟加拉国","views":30082,"rank":649},{"article":"返校","views":30071,"rank":650},{"article":"黃之鋒","views":30012,"rank":651},{"article":"櫻花大戰系列","views":30002,"rank":652},{"article":"黎明","views":29969,"rank":653},{"article":"凱羅·忍","views":29948,"rank":654},{"article":"亨利·卡維爾","views":29943,"rank":655},{"article":"約定的夢幻島","views":29897,"rank":656},{"article":"蘇花公路改善計畫","views":29895,"rank":657},{"article":"刘晓波","views":29894,"rank":658},{"article":"长征五号系列火箭","views":29870,"rank":659},{"article":"维吾尔族","views":29858,"rank":660},{"article":"辽宁号航空母舰","views":29858,"rank":660},{"article":"羅志祥","views":29854,"rank":662},{"article":"明英宗","views":29824,"rank":663},{"article":"觸及真心","views":29823,"rank":664},{"article":"东突厥斯坦","views":29794,"rank":665},{"article":"李小冉","views":29775,"rank":666},{"article":"Two Cops","views":29755,"rank":667},{"article":"邱義仁","views":29752,"rank":668},{"article":"用九柑仔店","views":29667,"rank":669},{"article":"呂珍九","views":29658,"rank":670},{"article":"武则天","views":29640,"rank":671},{"article":"黄明志","views":29608,"rank":672},{"article":"吳宗憲","views":29604,"rank":673},{"article":"奧卡菲娜","views":29594,"rank":674},{"article":"东宫 (电视剧)","views":29580,"rank":675},{"article":"鄧炳強","views":29573,"rank":676},{"article":"哆啦A夢","views":29539,"rank":677},{"article":"黑寡婦 (電影)","views":29508,"rank":678},{"article":"排球少年！！","views":29505,"rank":679},{"article":"大叔的愛","views":29490,"rank":680},{"article":"权力的游戏 (电视剧)","views":29485,"rank":681},{"article":"日食","views":29435,"rank":682},{"article":"國泰航空","views":29398,"rank":683},{"article":"陳信宏","views":29388,"rank":684},{"article":"米津玄師","views":29331,"rank":685},{"article":"玩命關頭：特別行動","views":29284,"rank":686},{"article":"Fate/stay night","views":29262,"rank":687},{"article":"Mnet亞洲音樂大獎","views":29250,"rank":688},{"article":"中国历史","views":29226,"rank":689},{"article":"水门事件","views":29201,"rank":691},{"article":"新世纪福音战士","views":29177,"rank":692},{"article":"航空母舰","views":29170,"rank":693},{"article":"华为","views":29156,"rank":694},{"article":"天气之子","views":29149,"rank":695},{"article":"泰勒·斯威夫特","views":29137,"rank":696},{"article":"婉君 (網絡用語)","views":29101,"rank":697},{"article":"中文维基百科","views":29076,"rank":698},{"article":"薛楷莉","views":29046,"rank":699},{"article":"中华人民共和国航空母舰建造计划","views":29022,"rank":700},{"article":"黑色五叶草","views":29018,"rank":701},{"article":"美國","views":29015,"rank":702},{"article":"第二次也很美","views":28965,"rank":703},{"article":"彭于晏","views":28958,"rank":704},{"article":"李多熙 (演員)","views":28929,"rank":705},{"article":"国内生产总值","views":28901,"rank":706},{"article":"胡善祥","views":28881,"rank":707},{"article":"李宰旭","views":28828,"rank":708},{"article":"車銀優","views":28802,"rank":709},{"article":"吳乃仁","views":28782,"rank":710},{"article":"金所泫","views":28724,"rank":711},{"article":"中国人民解放军海军","views":28724,"rank":711},{"article":"感恩节","views":28696,"rank":713},{"article":"上海市","views":28679,"rank":714},{"article":"碧藍航線","views":28669,"rank":715},{"article":"唐嫣","views":28667,"rank":716},{"article":"何庭歡","views":28658,"rank":717},{"article":"乃木坂46","views":28653,"rank":718},{"article":"萌獸寵物店","views":28630,"rank":719},{"article":"宋智孝","views":28603,"rank":720},{"article":"建文帝","views":28595,"rank":721},{"article":"阿部瑪利亞","views":28565,"rank":722},{"article":"花千骨","views":28530,"rank":723},{"article":"浪漫醫生金師傅","views":28472,"rank":724},{"article":"人間失格","views":28468,"rank":725},{"article":"反骨男孩","views":28463,"rank":726},{"article":"丁海寅","views":28455,"rank":727},{"article":"法国","views":28434,"rank":728},{"article":"輝夜姬想讓人告白～天才們的戀愛頭腦戰～","views":28430,"rank":729},{"article":"呂孫綾","views":28396,"rank":730},{"article":"九一一袭击事件","views":28387,"rank":731},{"article":"孔子","views":28385,"rank":732},{"article":"昆凌","views":28352,"rank":733},{"article":"石原聰美","views":28337,"rank":734},{"article":"朱斯·沃尔德","views":28320,"rank":735},{"article":"RION","views":28296,"rank":736},{"article":"猫 (音乐剧)","views":28270,"rank":737},{"article":"温貞菱","views":28264,"rank":738},{"article":"翁山蘇姬","views":28158,"rank":739},{"article":"彩虹的重力","views":28141,"rank":740},{"article":"芮","views":28116,"rank":741},{"article":"張基龍","views":28105,"rank":742},{"article":"張軒睿","views":28076,"rank":743},{"article":"Wanna One","views":28036,"rank":744},{"article":"Stray Kids","views":28023,"rank":745},{"article":"耶稣","views":27996,"rank":746},{"article":"林良 (臺灣作家)","views":27980,"rank":747},{"article":"金惠奫","views":27934,"rank":748},{"article":"孟晚舟","views":27913,"rank":749},{"article":"朴敘俊","views":27872,"rank":750},{"article":"林青霞","views":27868,"rank":751},{"article":"李嘉誠","views":27834,"rank":752},{"article":"2014年跨年夜上海外滩陈毅广场踩踏事件","views":27822,"rank":753},{"article":"火箭少女101","views":27802,"rank":754},{"article":"藍波：最後一滴血","views":27788,"rank":755},{"article":"潤娥","views":27716,"rank":757},{"article":"愛情是Beautiful，人生是Wonderful","views":27705,"rank":758},{"article":"嘉庆帝","views":27703,"rank":759},{"article":"东突厥斯坦独立运动","views":27683,"rank":760},{"article":"菲律宾","views":27630,"rank":761},{"article":"中華民國國民身分證","views":27579,"rank":762},{"article":"各国人均国民总收入列表","views":27576,"rank":763},{"article":"纳尔逊·曼德拉","views":27544,"rank":764},{"article":"牛下女高音","views":27530,"rank":765},{"article":"艾莎 (迪士尼)","views":27530,"rank":765},{"article":"莫文蔚","views":27524,"rank":767},{"article":"新北市","views":27523,"rank":768},{"article":"克里斯汀·貝爾","views":27522,"rank":769},{"article":"暗殺教室","views":27510,"rank":770},{"article":"中华人民共和国被封锁网站列表","views":27464,"rank":771},{"article":"自慰","views":27442,"rank":772},{"article":"清高宗继皇后","views":27389,"rank":773},{"article":"聲林之王2","views":27386,"rank":774},{"article":"欧洲联盟","views":27383,"rank":775},{"article":"防火长城","views":27367,"rank":776},{"article":"杨洋 (男演员)","views":27325,"rank":777},{"article":"蘭陵王 (電視劇)","views":27263,"rank":778},{"article":"中途岛海战","views":27230,"rank":779},{"article":"李榮浩","views":27192,"rank":780},{"article":"太宰治","views":27178,"rank":781},{"article":"張韶涵","views":27164,"rank":782},{"article":"七宗罪","views":27156,"rank":783},{"article":"Wikipedia","views":27115,"rank":784},{"article":"黃浩然","views":27046,"rank":785},{"article":"迈克尔·乔丹","views":27045,"rank":786},{"article":"成吉思汗","views":27023,"rank":787},{"article":"微微一笑很倾城 (电视剧)","views":27018,"rank":788},{"article":"行骗天下JP","views":27017,"rank":789},{"article":"紙房子","views":26969,"rank":790},{"article":"尤達","views":26967,"rank":791},{"article":"千千","views":26960,"rank":792},{"article":"瘋狂亞洲富豪","views":26936,"rank":793},{"article":"黃雋智","views":26935,"rank":794},{"article":"梅苏特·厄齐尔","views":26930,"rank":795},{"article":"李源潮","views":26901,"rank":796},{"article":"崔真理","views":26887,"rank":797},{"article":"臺灣白色恐怖時期","views":26878,"rank":798},{"article":"怪醫黑傑克","views":26862,"rank":799},{"article":"陳意涵","views":26854,"rank":800},{"article":"吳亦凡","views":26849,"rank":801},{"article":"那年花開月正圓","views":26829,"rank":802},{"article":"郑爽","views":26795,"rank":803},{"article":"費玉清","views":26788,"rank":804},{"article":"復興航空","views":26760,"rank":805},{"article":"IPhone","views":26728,"rank":806},{"article":"馬東石","views":26705,"rank":807},{"article":"寶島夢想家","views":26696,"rank":808},{"article":"西班牙","views":26689,"rank":809},{"article":"金正恩","views":26616,"rank":810},{"article":"李洪元案","views":26598,"rank":811},{"article":"孟晚舟事件","views":26535,"rank":812},{"article":"徐玄振","views":26530,"rank":813},{"article":"黃子華","views":26526,"rank":814},{"article":"李小龍","views":26526,"rank":814},{"article":"ONE PIECE角色列表","views":26483,"rank":816},{"article":"膜蛤文化","views":26483,"rank":816},{"article":"李连杰","views":26412,"rank":818},{"article":"楚乔传","views":26402,"rank":819},{"article":"周恩来","views":26393,"rank":820},{"article":"朴信惠","views":26333,"rank":821},{"article":"北京市","views":26315,"rank":822},{"article":"捍衛生死線","views":26282,"rank":823},{"article":"慈禧太后","views":26280,"rank":824},{"article":"臺北捷運","views":26266,"rank":825},{"article":"BLEACH","views":26260,"rank":826},{"article":"王菲","views":26252,"rank":827},{"article":"宸汐缘","views":26252,"rank":827},{"article":"范冰冰","views":26246,"rank":829},{"article":"博人传-火影次世代-","views":26241,"rank":830},{"article":"鄭若驊","views":26207,"rank":831},{"article":"觀看次數最多的YouTube影片列表","views":26168,"rank":832},{"article":"TFBOYS","views":26157,"rank":833},{"article":"他人即地狱","views":26123,"rank":834},{"article":"哈萨克斯坦","views":26120,"rank":835},{"article":"捍衛戰士","views":26112,"rank":836},{"article":"2018年中國退伍軍人鎮江市集體維權事件","views":26090,"rank":837},{"article":"锦衣之下","views":26066,"rank":838},{"article":"高雄負債","views":26063,"rank":839},{"article":"使徒行者3","views":25967,"rank":840},{"article":"利维亚的杰洛特","views":25949,"rank":841},{"article":"杨烁","views":25943,"rank":842},{"article":"蔡詩芸","views":25929,"rank":843},{"article":"全球最高電影票房","views":25925,"rank":844},{"article":"翡翠台電視劇集列表 (2020年代)","views":25914,"rank":845},{"article":"佩佩蛙","views":25882,"rank":846},{"article":"美心食品","views":25878,"rank":847},{"article":"黑死病","views":25863,"rank":848},{"article":"J.Sheon","views":25861,"rank":849},{"article":"鲍里斯·约翰逊","views":25860,"rank":850},{"article":"2020年美國總統選舉","views":25855,"rank":851},{"article":"高鈺婷","views":25848,"rank":852},{"article":"金正鉉 (1990年)","views":25841,"rank":853},{"article":"OVERLORD角色列表","views":25797,"rank":854},{"article":"黄浦江死猪漂流事件","views":25796,"rank":855},{"article":"帕金森氏症","views":25788,"rank":856},{"article":"佟梦实","views":25780,"rank":857},{"article":"对乙酰氨基酚","views":25779,"rank":858},{"article":"李香凝","views":25744,"rank":859},{"article":"黃心穎","views":25733,"rank":860},{"article":"诸葛亮","views":25703,"rank":861},{"article":"布洛芬","views":25666,"rank":862},{"article":"物联网","views":25666,"rank":862},{"article":"韩国电视剧列表","views":25654,"rank":864},{"article":"朴軫永","views":25653,"rank":865},{"article":"比特币","views":25616,"rank":866},{"article":"糖尿病","views":25604,"rank":867},{"article":"赵今麦","views":25585,"rank":868},{"article":"吉喆","views":25582,"rank":869},{"article":"003型航空母舰","views":25567,"rank":870},{"article":"趙少康","views":25549,"rank":871},{"article":"婁峻碩","views":25545,"rank":872},{"article":"台灣偶像劇列表","views":25519,"rank":873},{"article":"丁子高","views":25500,"rank":874},{"article":"新西遊記","views":25484,"rank":875},{"article":"路德维希·范·贝多芬","views":25454,"rank":876},{"article":"朱亚文","views":25452,"rank":877},{"article":"林宥嘉","views":25450,"rank":878},{"article":"台灣高鐵","views":25450,"rank":878},{"article":"尹立","views":25407,"rank":880},{"article":"馮紹峰","views":25395,"rank":881},{"article":"元朝","views":25392,"rank":882},{"article":"节气","views":25379,"rank":883},{"article":"郭佳怡","views":25356,"rank":884},{"article":"倚天屠龍記 (2019年電視劇)","views":25351,"rank":885},{"article":"苗栗縣議會","views":25350,"rank":886},{"article":"排屋公寓","views":25342,"rank":887},{"article":"朱庭萱","views":25334,"rank":888},{"article":"基督教","views":25324,"rank":889},{"article":"安宰賢","views":25304,"rank":890},{"article":"安雅·夏隆查","views":25283,"rank":891},{"article":"基努·里维斯","views":25273,"rank":892},{"article":"2018年Running Man節目列表","views":25260,"rank":893},{"article":"伊丽莎白·泰勒","views":25260,"rank":893},{"article":"全職高手 (網絡劇)","views":25221,"rank":895},{"article":"波多野結衣","views":25217,"rank":896},{"article":"吉米·霍法","views":25211,"rank":897},{"article":"珍珠港事件","views":25169,"rank":898},{"article":"賈靜雯","views":25169,"rank":898},{"article":"鄭宜農","views":25165,"rank":900},{"article":"2019年英國大選","views":25155,"rank":901},{"article":"中華民國立法委員選舉","views":25130,"rank":902},{"article":"Sex141","views":25101,"rank":903},{"article":"陳偉霆","views":25094,"rank":904},{"article":"汤唯","views":25089,"rank":905},{"article":"這群人TGOP","views":25081,"rank":906},{"article":"你的名字。","views":25074,"rank":907},{"article":"吳建豪","views":25033,"rank":908},{"article":"歐陽娜娜","views":25030,"rank":909},{"article":"乌克兰","views":25017,"rank":910},{"article":"亨利·高汀","views":25012,"rank":911},{"article":"何君堯","views":25001,"rank":912},{"article":"独孤天下","views":24915,"rank":913},{"article":"紫罗兰永恒花园","views":24896,"rank":914},{"article":"南宮珉","views":24861,"rank":915},{"article":"她的私生活","views":24850,"rank":916},{"article":"焦俊艳","views":24847,"rank":917},{"article":"平凡職業造就世界最強","views":24806,"rank":918},{"article":"罗晋","views":24782,"rank":919},{"article":"催眠·裁決","views":24765,"rank":920},{"article":"何如芸","views":24764,"rank":921},{"article":"霍建華","views":24753,"rank":922},{"article":"弒婚遊戲","views":24749,"rank":923},{"article":"阿拉丁 (2019年電影)","views":24740,"rank":924},{"article":"茄子蛋","views":24739,"rank":925},{"article":"花木兰 (2020年电影)","views":24736,"rank":926},{"article":"肖申克的救赎","views":24734,"rank":927},{"article":"HIStory (2017年電視劇)","views":24733,"rank":928},{"article":"隋炀帝","views":24697,"rank":929},{"article":"胡歌","views":24694,"rank":930},{"article":"摩洛哥","views":24690,"rank":931},{"article":"吳若希","views":24665,"rank":932},{"article":"揚尼斯·安戴托昆波","views":24658,"rank":933},{"article":"何志偉","views":24657,"rank":934},{"article":"中島美嘉","views":24618,"rank":935},{"article":"彭丽媛","views":24617,"rank":936},{"article":"隋朝","views":24583,"rank":937},{"article":"林秀晶","views":24569,"rank":938},{"article":"鲁迅","views":24535,"rank":939},{"article":"李千那","views":24533,"rank":940},{"article":"明日花綺羅","views":24501,"rank":941},{"article":"老挝","views":24490,"rank":942},{"article":"假面騎士系列","views":24488,"rank":943},{"article":"鈴木京香","views":24477,"rank":944},{"article":"古力娜扎","views":24451,"rank":945},{"article":"中国人民解放军","views":24439,"rank":946},{"article":"史蒂夫·乔布斯","views":24437,"rank":947},{"article":"潮吹","views":24437,"rank":947},{"article":"阿神","views":24425,"rank":949},{"article":"F.I.R.飛兒樂團","views":24391,"rank":950},{"article":"艾美莉·克拉克","views":24387,"rank":951},{"article":"李國豪 (演員)","views":24381,"rank":952},{"article":"薄瓜瓜","views":24368,"rank":953},{"article":"炎亞綸","views":24334,"rank":954},{"article":"周深","views":24321,"rank":955},{"article":"阿尔伯特·爱因斯坦","views":24317,"rank":956},{"article":"金庸","views":24310,"rank":957},{"article":"我們不能是朋友","views":24300,"rank":958},{"article":"鞠婧禕","views":24296,"rank":959},{"article":"湯姆·克魯斯","views":24287,"rank":960},{"article":"第十四世达赖喇嘛","views":24282,"rank":961},{"article":"LamiGirls","views":24263,"rank":962},{"article":"美国国会","views":24263,"rank":962},{"article":"決戰中途島","views":24251,"rank":964},{"article":"歡迎來到實力至上主義的教室","views":24229,"rank":965},{"article":"文森特·梵高","views":24221,"rank":966},{"article":"不起眼女主角培育法","views":24210,"rank":967},{"article":"聲林之王","views":24180,"rank":968},{"article":"飢餓遊戲 (電視節目)","views":24161,"rank":969},{"article":"生肖","views":24154,"rank":970},{"article":"許淑華 (南投縣)","views":24124,"rank":971},{"article":"小野賢章","views":24112,"rank":972},{"article":"港珠澳大橋","views":24098,"rank":973},{"article":"唐太宗","views":24097,"rank":974},{"article":"願榮光歸香港","views":24094,"rank":975},{"article":"李彥秀","views":24093,"rank":976},{"article":"我要做廚神 (美國版)","views":24092,"rank":977},{"article":"张学良","views":24059,"rank":978},{"article":"2019年12月逝世人物列表","views":24045,"rank":979},{"article":"請回答1988","views":24029,"rank":980},{"article":"山海经","views":24027,"rank":981},{"article":"中国抗日战争","views":24001,"rank":982},{"article":"張藝興","views":23977,"rank":984},{"article":"AKIRA","views":23977,"rank":984},{"article":"巫师 (游戏)","views":23957,"rank":986},{"article":"蝦皮購物","views":23938,"rank":987},{"article":"曹如晶","views":23929,"rank":988},{"article":"吴谨言","views":23929,"rank":988},{"article":"于美人","views":23923,"rank":990},{"article":"蕭美琴","views":23910,"rank":991},{"article":"獨孤伽羅","views":23866,"rank":992},{"article":"納粹德國","views":23832,"rank":993},{"article":"红楼梦","views":23831,"rank":994},{"article":"伊藤诗织","views":23826,"rank":995},{"article":"Apink","views":23814,"rank":996},{"article":"注音符號","views":23810,"rank":997},{"article":"何猷君","views":23769,"rank":998},{"article":"李白","views":23756,"rank":999},{"article":"岑子杰","views":23752,"rank":1000}]